network_connectivity_tester/__init__.py
network_connectivity_tester/awsclient.py
network_connectivity_tester/orchestrator.py
network_connectivity_tester/cli/__init__.py
network_connectivity_tester/cli/awsclient.py
network_connectivity_tester-0.3.0.dist-info/METADATA
network_connectivity_tester-0.3.0.dist-info/WHEEL
network_connectivity_tester-0.3.0.dist-info/entry_points.txt
network_connectivity_tester-0.3.0.dist-info/top_level.txt
network_connectivity_tester-0.3.0.dist-info/RECORD
