Metadata-Version: 2.1
Name: network-connectivity-tester
Version: 0.3.0
Summary: Test network connections between multiple instances and the internet using standard unit tests
Home-page: https://github.com/revenants-cie/network_connectivity_tester
Author: revenants-cie
Author-email: dev@revenants.net
License: UNKNOWN
Keywords: network_connectivity_tester
Platform: UNKNOWN
Classifier: Development Status :: 2 - Pre-Alpha
Classifier: Intended Audience :: Developers
Classifier: Natural Language :: English
Classifier: Programming Language :: Python :: 3
Classifier: Programming Language :: Python :: 3.7
Classifier: Programming Language :: Python :: 3.8
Requires-Python: >=3.5
Requires-Dist: boto3 (~=1.14)
Requires-Dist: cached-property (~=1.5)
Requires-Dist: Click (~=7.1)
Requires-Dist: docutils (<0.16,>=0.10)
Requires-Dist: python-daemon (~=2.2)
Requires-Dist: terraform-ci (~=1.3)
Requires-Dist: bump2version (~=1.0)
